{"access_token": "ya29.IlxxxxxxxxxTRB1QKPzGlaz4T6TxxxxxxxxxxuRwtrT0RwXA",
 "client_id": "xxxxxxxx-xxxxxxxxx.apps.googleusercontent.com",
 "client_secret": "Qqxxxxxxxxxxxxxk_",
 "refresh_token": "1//05kxxxxxxxxxxxxxxxxxxxxxsfY9vxxxxxxxxxxxxxxxxxxxxxxxxxg4k",
 "token_expiry": "2019-10-25T04:39:24Z",
 "token_uri": "https://oauth2.googleapis.com/token",
 "user_agent": null,
 "revoke_uri": "https://accounts.google.com/o/oauth2/revoke",
 "id_token": {"iss": "https://accounts.google.com",
	      "azp": "xxxxxxxxxxxx-fvxxxxxxxxxxxxxxxxxxxxx.apps.googleusercontent.com",
	      "aud": "xxxxxxxxxxxx-fvxxxxxxxxxxxxxxxxxxxxx.apps.googleusercontent.com",
	      "sub": "1xxxxxx",
	      "email": "ccs.helperbees@gmail.com",
	      "email_verified": true,
	      "at_hash": "Yn82XRwxxxxxxYA6UA",
	      "name": "Helper Bees",
	      "picture": "https://lh3.googleusercontent.com/a-/AAuE7mBkIuHW1Hqhl1cHwtafPIqXweFlkNZMmRD279r2=s96-c",
	      "given_name": "Helper", "family_name": "Bees", "locale": "en", "iat": 1571975113, "exp": 1571978713},
 "token_response": {"access_token": "yxxxxxxxxxxxxxxxxxxxPzGlaz4T6TiJyLZ4MxxxxxxxxxxwXA",
		    "expires_in": 3251,
		    "refresh_token": "1//05k7Ifxxxxxxxxxxxxxxxv3hGj9sfY9vi5S6kgxxxxxxxxxxxg4k",
		    "scope": "openid https://www.googleapis.com/auth/userinfo.profile https://www.googleapis.com/auth/gmail.send https://www.googleapis.com/auth/userinfo.email",
		    "token_type": "Bearer",
		    "id_token": "eyJhbGciOiJSUzI1NiIsImtpZCI6Ijhxxxxxxxxxxxxxxxxxxxw"},
 "scopes": ["https://www.googleapis.com/auth/gmail.send"],
 "token_info_uri": "https://www.googleapis.com/oauth2/v3/tokeninfo",
 "invalid": false,
 "_class": "OAuth2Credentials",
 "_module": "oauth2client.client"}
